<annotation verified="yes">
	<folder>alpaca</folder>
	<filename>alpaca175.jpg</filename>
	<path>C:\Giang\ObjectDetection\alpaca\alpaca175.jpg</path>
	<source>
		<database>Unknown</database>
	</source>
	<size>
		<width>1000</width>
		<height>669</height>
		<depth>3</depth>
	</size>
	<segmented>0</segmented>
	<object>
		<name>alpaca</name>
		<pose>Unspecified</pose>
		<truncated>0</truncated>
		<difficult>0</difficult>
		<bndbox>
			<xmin>206</xmin>
			<ymin>321</ymin>
			<xmax>778</xmax>
			<ymax>609</ymax>
		</bndbox>
	</object>
	<object>
		<name>alpaca</name>
		<pose>Unspecified</pose>
		<truncated>0</truncated>
		<difficult>0</difficult>
		<bndbox>
			<xmin>325</xmin>
			<ymin>6</ymin>
			<xmax>781</xmax>
			<ymax>484</ymax>
		</bndbox>
	</object>
</annotation>
